CHANGES.rst
MANIFEST.in
README.rst
setup.py
docs/LICENSE-GPL.rst
src/collective/__init__.py
src/collective.portlet.fullview.egg-info/PKG-INFO
src/collective.portlet.fullview.egg-info/SOURCES.txt
src/collective.portlet.fullview.egg-info/dependency_links.txt
src/collective.portlet.fullview.egg-info/entry_points.txt
src/collective.portlet.fullview.egg-info/namespace_packages.txt
src/collective.portlet.fullview.egg-info/not-zip-safe
src/collective.portlet.fullview.egg-info/requires.txt
src/collective.portlet.fullview.egg-info/top_level.txt
src/collective/portlet/__init__.py
src/collective/portlet/fullview/__init__.py
src/collective/portlet/fullview/configure.zcml
src/collective/portlet/fullview/fullview.pt
src/collective/portlet/fullview/fullview.py
src/collective/portlet/fullview/fullview_item.pt
src/collective/portlet/fullview/interfaces.py
src/collective/portlet/fullview/locales/MARKER
src/collective/portlet/fullview/locales/fi/LC_MESSAGES/collective.portlet.fullview.po
src/collective/portlet/fullview/locales/fi/LC_MESSAGES/plone.po
src/collective/portlet/fullview/profiles/default/browserlayer.xml
src/collective/portlet/fullview/profiles/default/metadata.xml
src/collective/portlet/fullview/profiles/default/portlets.xml
src/collective/portlet/fullview/profiles/uninstall/browserlayer.xml
src/collective/portlet/fullview/profiles/uninstall/portlets.xml