Metadata-Version: 1.1
Name: collective.portlet.fullview
Version: 2.0
Summary: Displays a content item as full view
Home-page: http://github.com/collective/collective.portlet.fullview
Author: Johannes Raggam
Author-email: johannes@raggam.co.at
License: GPL
Keywords: plone portlet
Platform: UNKNOWN
Classifier: Framework :: Plone
Classifier: Programming Language :: Python
